{
    "format_version": "1.21.60",
    "minecraft:block": {
        "description": {
            "identifier": "dec:nether_dandelion_crop"
        },
        "components": {
            "minecraft:material_instances": {
                "*": {
                    "texture": "nether_dandelion_crop",
                    "render_method": "alpha_test"
                }
            },
            "minecraft:geometry": "geometry.crop.sparse.on_dirt",
            "minecraft:collision_box": false,
            "minecraft:selection_box": {
                "origin": [
                    -5,
                    0,
                    -5
                ],
                "size": [
                    10,
                    15,
                    10
                ]
            },
            "minecraft:destructible_by_mining": {
                "seconds_to_destroy": 0.001
            },
            "minecraft:map_color": "#59c135",
            "minecraft:light_dampening": 0.0,
            "minecraft:loot": "loot_tables/blocks/nether_dandelion_crop.json",
            "minecraft:placement_filter": {
                "conditions": [
                    {
                        "allowed_faces": [
                            "up"
                        ],
                        "block_filter": [
                            "netherrack",
                            "nether_wart_block",
                            "crimson_nylium"
                        ]
                    }
                ]
            }
        }
    }
}