{
    "format_version": "1.16.100",
    "minecraft:item": {
        "description": {
            "identifier": "epic:machanical_operator",
            "category": "equipment"
        },
        "components": {
            "minecraft:creative_category": {
                "parent": "itemGroup.name.sword"
            },
            "minecraft:display_name": {
                // "value": "机械操纵者"
                "value": "item.epic:machanical_operator.name"
            },
            "minecraft:icon": {
                "texture": "epic:machanical_operator"
            },
            "minecraft:render_offsets": {
                "main_hand": {
                    "first_person": {
                        "scale": [
                            0.01,
                            0.006,
                            0.01
                        ]
                    },
                    "third_person": {
                        "position": [
                            0.45,
                            1.6,
                            -0.7
                        ],
                        "scale": [
                            0.03125,
                            0.01825,
                            0.03125
                        ]
                    }
                },
                "off_hand": {
                    "first_person": {
                        "position": [
                            0,
                            0,
                            0
                        ],
                        "rotation": [
                            0,
                            0,
                            0
                        ],
                        "scale": [
                            0,
                            0,
                            0
                        ]
                    },
                    "third_person": {
                        "position": [
                            0,
                            0,
                            0
                        ],
                        "rotation": [
                            0,
                            0,
                            0
                        ],
                        "scale": [
                            0,
                            0,
                            0
                        ]
                    }
                }
            },

            "minecraft:stacked_by_data": false,
            "minecraft:max_stack_size": 1,
            "minecraft:hand_equipped": true,
            "minecraft:on_use": {},
            "events": {

            }
        }
    }
}