{
    "format_version": "1.21.94",
    "minecraft:item": {
        "description": {
            "identifier": "dec:flintlock_bullet",
            "menu_category": {
                "group": "dec:itemGroup.name.bullets",
                "is_hidden_in_commands": false,
                "category": "equipment"
            }
        },
        "components": {
            "minecraft:display_name": {
                "value": "item.dec:flintlock_bullet.name"
            },
            "minecraft:use_animation": "eat",
            "minecraft:allow_off_hand": true,
            "minecraft:icon": {
                "textures": {
                    "default": "flintlock_bullet"
                }
            }
        }
    }
}