{
    "format_version": "1.20.80",
    "minecraft:block": {
        "description": {
            "identifier": "dec:cave_crate",
            "states": {
                "dec:is_unlocked": [
                    0,
                    1
                ]
            },
            "menu_category": {
                "group": "itemGroup.name.outside",
                "category": "items"
            }
        },
        "components": {
            "minecraft:light_dampening": 15,
            "minecraft:light_emission": 0,
            "minecraft:destructible_by_mining": {
                "seconds_to_destroy": 2.2
            },
            "minecraft:destructible_by_explosion": {
                "explosion_resistance": 10
            },
            "minecraft:map_color": "#6E6B66",
            "minecraft:geometry": "minecraft:geometry.full_block",
            "tag:wood": {}
        },
        "permutations": [
            {
                "condition": "query.block_state('dec:is_unlocked') == 0",
                "components": {
                    "minecraft:material_instances": {
                        "*": {
                            "texture": "cave_crate_locked",
                            "render_method": "opaque"
                        }
                    },
                    "minecraft:loot": "loot_tables/blocks/cave_crate_locked.json",
                    "minecraft:custom_components": [
                        "ex:on_interact"
                    ]
                }
            },
            {
                "condition": "query.block_state('dec:is_unlocked') == 1",
                "components": {
                    "minecraft:material_instances": {
                        "*": {
                            "texture": "cave_crate",
                            "render_method": "opaque"
                        }
                    },
                    "minecraft:loot": "loot_tables/blocks/cave_crate.json"
                }
            }
        ]
    }
}